pyetldb/__init__.py
pyetldb/pyetldb.py
pyetldb-0.1.dist-info/LICENSE.md
pyetldb-0.1.dist-info/METADATA
pyetldb-0.1.dist-info/WHEEL
pyetldb-0.1.dist-info/top_level.txt
pyetldb-0.1.dist-info/RECORD
