Metadata-Version: 2.1
Name: pyetldb
Version: 0.1
Summary: Python module that allows an easy interconnection between Microsoft Access and a support server for SQL with data sync
Home-page: https://github.com/natanaelfneto/pyetldb
Author: natanaelfneto
Author-email: natanaelfneto@outlook.com
License: MIT
Platform: UNKNOWN
Classifier: Programming Language :: Python :: 3
Classifier: License :: OSI Approved :: MIT License
Classifier: Operating System :: OS Independent
Requires-Dist: cx-Oracle
Requires-Dist: mysqlclient
Requires-Dist: psycopg2
Requires-Dist: pyodbc
Requires-Dist: pypyodbc
